<annotation>
	<folder>to_send</folder>
	<filename>Image_64.jpeg</filename>
	<path>C:\Users\Deepesh\Desktop\to_send\Image_64.jpeg</path>
	<source>
		<database>Unknown</database>
	</source>
	<size>
		<width>760</width>
		<height>1020</height>
		<depth>3</depth>
	</size>
	<segmented>0</segmented>
	<object>
		<name>document</name>
		<pose>Unspecified</pose>
		<truncated>0</truncated>
		<difficult>0</difficult>
		<bndbox>
			<xmin>118</xmin>
			<ymin>110</ymin>
			<xmax>665</xmax>
			<ymax>928</ymax>
		</bndbox>
	</object>
</annotation>
